{
    "round": 17,
    "j1_matches": [
        {
            "home": "歌川アリアーレ",
            "away": "城島セレーナ",
            "home_score": null,
            "away_score": null,
            "home_scorers": [],
            "away_scorers": []
        },
        {
            "home": "千都アルディーレ",
            "away": "フェリダ虹吹",
            "home_score": null,
            "away_score": null,
            "home_scorers": [],
            "away_scorers": []
        },
        {
            "home": "ルシエル星丘",
            "away": "鶴牧ブリランテ",
            "home_score": null,
            "away_score": null,
            "home_scorers": [],
            "away_scorers": []
        },
        {
            "home": "浜見デルマーレ",
            "away": "ルセリオ峰岡",
            "home_score": null,
            "away_score": null,
            "home_scorers": [],
            "away_scorers": []
        },
        {
            "home": "美里フロリスFC",
            "away": "都井沢レガリスタ",
            "home_score": null,
            "away_score": null,
            "home_scorers": [],
            "away_scorers": []
        },
        {
            "home": "エルネスタ永山FC",
            "away": "七沢ユノセラ",
            "home_score": null,
            "away_score": null,
            "home_scorers": [],
            "away_scorers": []
        },
        {
            "home": "六辻ヴェルティア",
            "away": "大神エスペランザ",
            "home_score": null,
            "away_score": null,
            "home_scorers": [],
            "away_scorers": []
        },
        {
            "home": "都井沢マリリオ",
            "away": "桃浜ロゼルナ",
            "home_score": null,
            "away_score": null,
            "home_scorers": [],
            "away_scorers": []
        },
        {
            "home": "国分FC",
            "away": "千都レイヴンス",
            "home_score": null,
            "away_score": null,
            "home_scorers": [],
            "away_scorers": []
        }
    ],
    "j2_matches": [
        {
            "home": "影取カーヴェリオ",
            "away": "セルヴァ鵜野森",
            "home_score": null,
            "away_score": null,
            "home_scorers": [],
            "away_scorers": []
        },
        {
            "home": "月夜野セレネFC",
            "away": "成木シティFC",
            "home_score": null,
            "away_score": null,
            "home_scorers": [],
            "away_scorers": []
        },
        {
            "home": "浜岳セルヴェリオ",
            "away": "八重咲ヴェルメリア",
            "home_score": null,
            "away_score": null,
            "home_scorers": [],
            "away_scorers": []
        },
        {
            "home": "江東ヴィアージュ",
            "away": "若洲アズール",
            "home_score": null,
            "away_score": null,
            "home_scorers": [],
            "away_scorers": []
        },
        {
            "home": "滝沢カスケーダ",
            "away": "クラリーダ夏島",
            "home_score": null,
            "away_score": null,
            "home_scorers": [],
            "away_scorers": []
        },
        {
            "home": "香柏ルヴァーナ",
            "away": "内海FC",
            "home_score": null,
            "away_score": null,
            "home_scorers": [],
            "away_scorers": []
        },
        {
            "home": "柚木ソリス",
            "away": "アストラル月夜野",
            "home_score": null,
            "away_score": null,
            "home_scorers": [],
            "away_scorers": []
        },
        {
            "home": "梅郷アマリリス",
            "away": "FC山吹",
            "home_score": null,
            "away_score": null,
            "home_scorers": [],
            "away_scorers": []
        },
        {
            "home": "渡内ユナイテッド",
            "away": "城南レイクランツ",
            "home_score": null,
            "away_score": null,
            "home_scorers": [],
            "away_scorers": []
        },
        {
            "home": "ヴァルゴラ辻山",
            "away": "吉野浜ルーチェ",
            "home_score": null,
            "away_score": null,
            "home_scorers": [],
            "away_scorers": []
        }
    ]
}